grammarian/__init__.py
grammarian/src/Makefile
grammarian/src/__init__.py
grammarian/src/grammar.so
grammarian/src/grammarian.py
grammarian/src/words_alpha.txt
grammarian/src/utilities/__init__.py
grammarian/src/utilities/grammarian_check.py
grammarian/src/utilities/grammarian_exception.py
grammarian-0.2.1.dist-info/licenses/LICENSE.txt
grammarian-0.2.1.dist-info/METADATA
grammarian-0.2.1.dist-info/WHEEL
grammarian-0.2.1.dist-info/top_level.txt
grammarian-0.2.1.dist-info/RECORD
