Metadata-Version: 2.4
Name: grammarian
Version: 0.2.1
Summary: An easy and fast tool to check english grammar
Home-page: https://github.com/hiko667/grammarian-grammar-checker-package
Author: StanisławKulesza
License: MIT
Classifier: License :: OSI Approved :: MIT License
Classifier: Programming Language :: Python :: 3.13
Classifier: Operating System :: OS Independent
Requires-Python: >=3.13
License-File: LICENSE.txt
Provides-Extra: dev
Requires-Dist: twine>=6.2.0; extra == "dev"
Dynamic: author
Dynamic: classifier
Dynamic: description
Dynamic: description-content-type
Dynamic: home-page
Dynamic: license
Dynamic: license-file
Dynamic: provides-extra
Dynamic: requires-python
Dynamic: summary
